seqLogic/upDownCounter/counter4.v
module counter4(
    input clk, 
    input rst, 
    input up_down, //clock, reset, 1 = up, 0 = down
    output reg [3:0] q
);
    always@(posedge clk) begin
        if(rst)
            q <= 4'b0000; //reset counter
        else if(up_down)
            q <= q+1;
        else
            q <= q-1;
    end
endmodule

seqLogic/upDownCounter/tb_counter.v
module tb_counter;
    reg clk;
    reg rst;
    reg up_down;
    wire [3:0] count;

    //instatiate the counter
    counter4  my_counter(
        .clk(clk),
        .rst(rst),
        .up_down(up_down),
        .q(count)
    );

    initial begin
        clk = 0;
        forever #5 clk = ~clk ;
    end

    initial begin
        rst = 1;
        up_down = 1;
        #20
        rst = 0;
        #100
        up_down = 0;
        #100
        $finish;
    end

    always @(posedge clk) begin
        $display("Time = %0t |rst=%b| up_down = %b | count = %b (%0d)", $time, rst, up_down, count, count);
    end

    initial begin
        $dumpfile("tb_counter.vcd");
        $dumpvars(0,tb_counter);
    end
endmodule

seqLogic/upDownCounter/tb_counter.vcd
$date
	Sat Aug 30 14:10:18 2025
$end
$version
	Icarus Verilog
$end
$timescale
	1s
$end
$scope module tb_counter $end
$var wire 4 ! count [3:0] $end
$var reg 1 " clk $end
$var reg 1 # rst $end
$var reg 1 $ up_down $end
$scope module my_counter $end
$var wire 1 " clk $end
$var wire 1 # rst $end
$var wire 1 $ up_down $end
$var reg 4 % q [3:0] $end
$upscope $end
$upscope $end
$enddefinitions $end
$comment Show the parameter values. $end
$dumpall
$end
#0
$dumpvars
bx %
1$
1#
0"
bx !
$end
#5
b0 !
b0 %
1"
#10
0"
#15
1"
#20
0"
0#
#25
b1 !
b1 %
1"
#30
0"
#35
b10 !
b10 %
1"
#40
0"
#45
b11 !
b11 %
1"
#50
0"
#55
b100 !
b100 %
1"
#60
0"
#65
b101 !
b101 %
1"
#70
0"
#75
b110 !
b110 %
1"
#80
0"
#85
b111 !
b111 %
1"
#90
0"
#95
b1000 !
b1000 %
1"
#100
0"
#105
b1001 !
b1001 %
1"
#110
0"
#115
b1010 !
b1010 %
1"
#120
0"
0$
#125
b1001 !
b1001 %
1"
#130
0"
#135
b1000 !
b1000 %
1"
#140
0"
#145
b111 !
b111 %
1"
#150
0"
#155
b110 !
b110 %
1"
#160
0"
#165
b101 !
b101 %
1"
#170
0"
#175
b100 !
b100 %
1"
#180
0"
#185
b11 !
b11 %
1"
#190
0"
#195
b10 !
b10 %
1"
#200
0"
#205
b1 !
b1 %
1"
#210
0"
#215
b0 !
b0 %
1"
