combLogic/4bitAdder/src/adder4.v
/* verilator lint_off DECLFILENAME */
module adder4(
    input wire [3:0] a,
    input wire [3:0] b,
    output wire [3:0] sum,
    output wire c_out
);
    wire c1,c2,c3; //carry wires
    full_adder fa0(.a(a[0]),.b(b[0]), .cin(1'b0), .sum(sum[0]), .cout(c1));
    full_adder fa1(.a(a[1]),.b(b[1]), .cin(c1), .sum(sum[1]), .cout(c2));
    full_adder fa2(.a(a[2]),.b(b[2]), .cin(c2), .sum(sum[2]), .cout(c3));
    full_adder fa3(.a(a[3]),.b(b[3]), .cin(c3), .sum(sum[3]), .cout(c_out));
endmodule
module full_adder(
    input wire a,b,cin,
    output wire sum, cout
);
    assign sum = a^b^cin;
    assign cout = a&b | a&cin | b&cin;
endmodule
/* verilator lint_on DECLFILENAME */

combLogic/4bitAdder/src/adder4.vcd
$version Generated by VerilatedVcd $end
$date Sat Aug 30 13:28:12 2025 $end
$timescale 1ps $end

 $scope module TOP $end
  $var wire  4 & a [3:0] $end
  $var wire  4 ' b [3:0] $end
  $var wire  1 ) c_out $end
  $var wire  4 ( sum [3:0] $end
  $scope module adder4 $end
   $var wire  4 & a [3:0] $end
   $var wire  4 ' b [3:0] $end
   $var wire  1 # c1 $end
   $var wire  1 $ c2 $end
   $var wire  1 % c3 $end
   $var wire  1 ) c_out $end
   $var wire  4 ( sum [3:0] $end
   $scope module fa0 $end
    $var wire  1 * a $end
    $var wire  1 + b $end
    $var wire  1 6 cin $end
    $var wire  1 # cout $end
    $var wire  1 , sum $end
   $upscope $end
   $scope module fa1 $end
    $var wire  1 - a $end
    $var wire  1 . b $end
    $var wire  1 # cin $end
    $var wire  1 $ cout $end
    $var wire  1 / sum $end
   $upscope $end
   $scope module fa2 $end
    $var wire  1 0 a $end
    $var wire  1 1 b $end
    $var wire  1 $ cin $end
    $var wire  1 % cout $end
    $var wire  1 2 sum $end
   $upscope $end
   $scope module fa3 $end
    $var wire  1 3 a $end
    $var wire  1 4 b $end
    $var wire  1 % cin $end
    $var wire  1 ) cout $end
    $var wire  1 5 sum $end
   $upscope $end
  $upscope $end
 $upscope $end
$enddefinitions $end


#0
0#
0$
0%
b0000 &
b0000 '
b0000 (
0)
0*
0+
0,
0-
0.
0/
00
01
02
03
04
05
06
#1
b0001 '
b0001 (
1+
1,
#2
b0010 '
b0010 (
0+
0,
1.
1/
#3
b0011 '
b0011 (
1+
1,
#4
b0100 '
b0100 (
0+
0,
0.
0/
11
12
#5
b0101 '
b0101 (
1+
1,
#6
b0110 '
b0110 (
0+
0,
1.
1/
#7
b0111 '
b0111 (
1+
1,
#8
b1000 '
b1000 (
0+
0,
0.
0/
01
02
14
15
#9
b1001 '
b1001 (
1+
1,
#10
b1010 '
b1010 (
0+
0,
1.
1/
#11
b1011 '
b1011 (
1+
1,
#12
b1100 '
b1100 (
0+
0,
0.
0/
11
12
#13
b1101 '
b1101 (
1+
1,
#14
b1110 '
b1110 (
0+
0,
1.
1/
#15
b1111 '
b1111 (
1+
1,
#16
b0001 &
b0000 '
b0001 (
1*
0+
0.
0/
01
02
04
05
#17
1#
b0001 '
b0010 (
1+
0,
1/
#18
0#
b0010 '
b0011 (
0+
1,
1.
#19
1#
1$
b0011 '
b0100 (
1+
0,
0/
12
#20
0#
0$
b0100 '
b0101 (
0+
1,
0.
11
#21
1#
b0101 '
b0110 (
1+
0,
1/
#22
0#
b0110 '
b0111 (
0+
1,
1.
#23
1#
1$
1%
b0111 '
b1000 (
1+
0,
0/
02
15
#24
0#
0$
0%
b1000 '
b1001 (
0+
1,
0.
01
14
#25
1#
b1001 '
b1010 (
1+
0,
1/
#26
0#
b1010 '
b1011 (
0+
1,
1.
#27
1#
1$
b1011 '
b1100 (
1+
0,
0/
12
#28
0#
0$
b1100 '
b1101 (
0+
1,
0.
11
#29
1#
b1101 '
b1110 (
1+
0,
1/
#30
0#
b1110 '
b1111 (
0+
1,
1.
#31
1#
1$
1%
b1111 '
b0000 (
1)
1+
0,
0/
02
05
#32
0#
0$
0%
b0010 &
b0000 '
b0010 (
0)
0*
0+
1-
0.
1/
01
04
#33
b0001 '
b0011 (
1+
1,
#34
1$
b0010 '
b0100 (
0+
0,
1.
0/
12
#35
b0011 '
b0101 (
1+
1,
#36
0$
b0100 '
b0110 (
0+
0,
0.
1/
11
#37
b0101 '
b0111 (
1+
1,
#38
1$
1%
b0110 '
b1000 (
0+
0,
1.
0/
02
15
#39
b0111 '
b1001 (
1+
1,
#40
0$
0%
b1000 '
b1010 (
0+
0,
0.
1/
01
14
#41
b1001 '
b1011 (
1+
1,
#42
1$
b1010 '
b1100 (
0+
0,
1.
0/
12
#43
b1011 '
b1101 (
1+
1,
#44
0$
b1100 '
b1110 (
0+
0,
0.
1/
11
#45
b1101 '
b1111 (
1+
1,
#46
1$
1%
b1110 '
b0000 (
1)
0+
0,
1.
0/
02
05
#47
b1111 '
b0001 (
1+
1,
#48
0$
0%
b0011 &
b0000 '
b0011 (
0)
1*
0+
0.
1/
01
04
#49
1#
1$
b0001 '
b0100 (
1+
0,
0/
12
#50
0#
b0010 '
b0101 (
0+
1,
1.
#51
1#
b0011 '
b0110 (
1+
0,
1/
#52
0#
0$
b0100 '
b0111 (
0+
1,
0.
11
#53
1#
1$
1%
b0101 '
b1000 (
1+
0,
0/
02
15
#54
0#
b0110 '
b1001 (
0+
1,
1.
#55
1#
b0111 '
b1010 (
1+
0,
1/
#56
0#
0$
0%
b1000 '
b1011 (
0+
1,
0.
01
14
#57
1#
1$
b1001 '
b1100 (
1+
0,
0/
12
#58
0#
b1010 '
b1101 (
0+
1,
1.
#59
1#
b1011 '
b1110 (
1+
0,
1/
#60
0#
0$
b1100 '
b1111 (
0+
1,
0.
11
#61
1#
1$
1%
b1101 '
b0000 (
1)
1+
0,
0/
02
05
#62
0#
b1110 '
b0001 (
0+
1,
1.
#63
1#
b1111 '
b0010 (
1+
0,
1/
#64
0#
0$
0%
b0100 &
b0000 '
b0100 (
0)
0*
0+
0-
0.
0/
10
01
12
04
#65
b0001 '
b0101 (
1+
1,
#66
b0010 '
b0110 (
0+
0,
1.
1/
#67
b0011 '
b0111 (
1+
1,
#68
1%
b0100 '
b1000 (
0+
0,
0.
0/
11
02
15
#69
b0101 '
b1001 (
1+
1,
#70
b0110 '
b1010 (
0+
0,
1.
1/
#71
b0111 '
b1011 (
1+
1,
#72
0%
b1000 '
b1100 (
0+
0,
0.
0/
01
12
14
#73
b1001 '
b1101 (
1+
1,
#74
b1010 '
b1110 (
0+
0,
1.
1/
#75
b1011 '
b1111 (
1+
1,
#76
1%
b1100 '
b0000 (
1)
0+
0,
0.
0/
11
02
05
#77
b1101 '
b0001 (
1+
1,
#78
b1110 '
b0010 (
0+
0,
1.
1/
#79
b1111 '
b0011 (
1+
1,
#80
0%
b0101 &
b0000 '
b0101 (
0)
1*
0+
0.
0/
01
12
04
#81
1#
b0001 '
b0110 (
1+
0,
1/
#82
0#
b0010 '
b0111 (
0+
1,
1.
#83
1#
1$
1%
b0011 '
b1000 (
1+
0,
0/
02
15
#84
0#
0$
b0100 '
b1001 (
0+
1,
0.
11
#85
1#
b0101 '
b1010 (
1+
0,
1/
#86
0#
b0110 '
b1011 (
0+
1,
1.
#87
1#
1$
b0111 '
b1100 (
1+
0,
0/
12
#88
0#
0$
0%
b1000 '
b1101 (
0+
1,
0.
01
14
#89
1#
b1001 '
b1110 (
1+
0,
1/
#90
0#
b1010 '
b1111 (
0+
1,
1.
#91
1#
1$
1%
b1011 '
b0000 (
1)
1+
0,
0/
02
05
#92
0#
0$
b1100 '
b0001 (
0+
1,
0.
11
#93
1#
b1101 '
b0010 (
1+
0,
1/
#94
0#
b1110 '
b0011 (
0+
1,
1.
#95
1#
1$
b1111 '
b0100 (
1+
0,
0/
12
#96
0#
0$
0%
b0110 &
b0000 '
b0110 (
0)
0*
0+
1-
0.
1/
01
04
#97
b0001 '
b0111 (
1+
1,
#98
1$
1%
b0010 '
b1000 (
0+
0,
1.
0/
02
15
#99
b0011 '
b1001 (
1+
1,
#100
0$
b0100 '
b1010 (
0+
0,
0.
1/
11
#101
b0101 '
b1011 (
1+
1,
#102
1$
b0110 '
b1100 (
0+
0,
1.
0/
12
#103
b0111 '
b1101 (
1+
1,
#104
0$
0%
b1000 '
b1110 (
0+
0,
0.
1/
01
14
#105
b1001 '
b1111 (
1+
1,
#106
1$
1%
b1010 '
b0000 (
1)
0+
0,
1.
0/
02
05
#107
b1011 '
b0001 (
1+
1,
#108
0$
b1100 '
b0010 (
0+
0,
0.
1/
11
#109
b1101 '
b0011 (
1+
1,
#110
1$
b1110 '
b0100 (
0+
0,
1.
0/
12
#111
b1111 '
b0101 (
1+
1,
#112
0$
0%
b0111 &
b0000 '
b0111 (
0)
1*
0+
0.
1/
01
04
#113
1#
1$
1%
b0001 '
b1000 (
1+
0,
0/
02
15
#114
0#
b0010 '
b1001 (
0+
1,
1.
#115
1#
b0011 '
b1010 (
1+
0,
1/
#116
0#
0$
b0100 '
b1011 (
0+
1,
0.
11
#117
1#
1$
b0101 '
b1100 (
1+
0,
0/
12
#118
0#
b0110 '
b1101 (
0+
1,
1.
#119
1#
b0111 '
b1110 (
1+
0,
1/
#120
0#
0$
0%
b1000 '
b1111 (
0+
1,
0.
01
14
#121
1#
1$
1%
b1001 '
b0000 (
1)
1+
0,
0/
02
05
#122
0#
b1010 '
b0001 (
0+
1,
1.
#123
1#
b1011 '
b0010 (
1+
0,
1/
#124
0#
0$
b1100 '
b0011 (
0+
1,
0.
11
#125
1#
1$
b1101 '
b0100 (
1+
0,
0/
12
#126
0#
b1110 '
b0101 (
0+
1,
1.
#127
1#
b1111 '
b0110 (
1+
0,
1/
#128
0#
0$
0%
b1000 &
b0000 '
b1000 (
0)
0*
0+
0-
0.
0/
00
01
02
13
04
15
#129
b0001 '
b1001 (
1+
1,
#130
b0010 '
b1010 (
0+
0,
1.
1/
#131
b0011 '
b1011 (
1+
1,
#132
b0100 '
b1100 (
0+
0,
0.
0/
11
12
#133
b0101 '
b1101 (
1+
1,
#134
b0110 '
b1110 (
0+
0,
1.
1/
#135
b0111 '
b1111 (
1+
1,
#136
b1000 '
b0000 (
1)
0+
0,
0.
0/
01
02
14
05
#137
b1001 '
b0001 (
1+
1,
#138
b1010 '
b0010 (
0+
0,
1.
1/
#139
b1011 '
b0011 (
1+
1,
#140
b1100 '
b0100 (
0+
0,
0.
0/
11
12
#141
b1101 '
b0101 (
1+
1,
#142
b1110 '
b0110 (
0+
0,
1.
1/
#143
b1111 '
b0111 (
1+
1,
#144
b1001 &
b0000 '
b1001 (
0)
1*
0+
0.
0/
01
02
04
15
#145
1#
b0001 '
b1010 (
1+
0,
1/
#146
0#
b0010 '
b1011 (
0+
1,
1.
#147
1#
1$
b0011 '
b1100 (
1+
0,
0/
12
#148
0#
0$
b0100 '
b1101 (
0+
1,
0.
11
#149
1#
b0101 '
b1110 (
1+
0,
1/
#150
0#
b0110 '
b1111 (
0+
1,
1.
#151
1#
1$
1%
b0111 '
b0000 (
1)
1+
0,
0/
02
05
#152
0#
0$
0%
b1000 '
b0001 (
0+
1,
0.
01
14
#153
1#
b1001 '
b0010 (
1+
0,
1/
#154
0#
b1010 '
b0011 (
0+
1,
1.
#155
1#
1$
b1011 '
b0100 (
1+
0,
0/
12
#156
0#
0$
b1100 '
b0101 (
0+
1,
0.
11
#157
1#
b1101 '
b0110 (
1+
0,
1/
#158
0#
b1110 '
b0111 (
0+
1,
1.
#159
1#
1$
1%
b1111 '
b1000 (
1+
0,
0/
02
15
#160
0#
0$
0%
b1010 &
b0000 '
b1010 (
0)
0*
0+
1-
0.
1/
01
04
#161
b0001 '
b1011 (
1+
1,
#162
1$
b0010 '
b1100 (
0+
0,
1.
0/
12
#163
b0011 '
b1101 (
1+
1,
#164
0$
b0100 '
b1110 (
0+
0,
0.
1/
11
#165
b0101 '
b1111 (
1+
1,
#166
1$
1%
b0110 '
b0000 (
1)
0+
0,
1.
0/
02
05
#167
b0111 '
b0001 (
1+
1,
#168
0$
0%
b1000 '
b0010 (
0+
0,
0.
1/
01
14
#169
b1001 '
b0011 (
1+
1,
#170
1$
b1010 '
b0100 (
0+
0,
1.
0/
12
#171
b1011 '
b0101 (
1+
1,
#172
0$
b1100 '
b0110 (
0+
0,
0.
1/
11
#173
b1101 '
b0111 (
1+
1,
#174
1$
1%
b1110 '
b1000 (
0+
0,
1.
0/
02
15
#175
b1111 '
b1001 (
1+
1,
#176
0$
0%
b1011 &
b0000 '
b1011 (
0)
1*
0+
0.
1/
01
04
#177
1#
1$
b0001 '
b1100 (
1+
0,
0/
12
#178
0#
b0010 '
b1101 (
0+
1,
1.
#179
1#
b0011 '
b1110 (
1+
0,
1/
#180
0#
0$
b0100 '
b1111 (
0+
1,
0.
11
#181
1#
1$
1%
b0101 '
b0000 (
1)
1+
0,
0/
02
05
#182
0#
b0110 '
b0001 (
0+
1,
1.
#183
1#
b0111 '
b0010 (
1+
0,
1/
#184
0#
0$
0%
b1000 '
b0011 (
0+
1,
0.
01
14
#185
1#
1$
b1001 '
b0100 (
1+
0,
0/
12
#186
0#
b1010 '
b0101 (
0+
1,
1.
#187
1#
b1011 '
b0110 (
1+
0,
1/
#188
0#
0$
b1100 '
b0111 (
0+
1,
0.
11
#189
1#
1$
1%
b1101 '
b1000 (
1+
0,
0/
02
15
#190
0#
b1110 '
b1001 (
0+
1,
1.
#191
1#
b1111 '
b1010 (
1+
0,
1/
#192
0#
0$
0%
b1100 &
b0000 '
b1100 (
0)
0*
0+
0-
0.
0/
10
01
12
04
#193
b0001 '
b1101 (
1+
1,
#194
b0010 '
b1110 (
0+
0,
1.
1/
#195
b0011 '
b1111 (
1+
1,
#196
1%
b0100 '
b0000 (
1)
0+
0,
0.
0/
11
02
05
#197
b0101 '
b0001 (
1+
1,
#198
b0110 '
b0010 (
0+
0,
1.
1/
#199
b0111 '
b0011 (
1+
1,
#200
0%
b1000 '
b0100 (
0+
0,
0.
0/
01
12
14
#201
b1001 '
b0101 (
1+
1,
#202
b1010 '
b0110 (
0+
0,
1.
1/
#203
b1011 '
b0111 (
1+
1,
#204
1%
b1100 '
b1000 (
0+
0,
0.
0/
11
02
15
#205
b1101 '
b1001 (
1+
1,
#206
b1110 '
b1010 (
0+
0,
1.
1/
#207
b1111 '
b1011 (
1+
1,
#208
0%
b1101 &
b0000 '
b1101 (
0)
1*
0+
0.
0/
01
12
04
#209
1#
b0001 '
b1110 (
1+
0,
1/
#210
0#
b0010 '
b1111 (
0+
1,
1.
#211
1#
1$
1%
b0011 '
b0000 (
1)
1+
0,
0/
02
05
#212
0#
0$
b0100 '
b0001 (
0+
1,
0.
11
#213
1#
b0101 '
b0010 (
1+
0,
1/
#214
0#
b0110 '
b0011 (
0+
1,
1.
#215
1#
1$
b0111 '
b0100 (
1+
0,
0/
12
#216
0#
0$
0%
b1000 '
b0101 (
0+
1,
0.
01
14
#217
1#
b1001 '
b0110 (
1+
0,
1/
#218
0#
b1010 '
b0111 (
0+
1,
1.
#219
1#
1$
1%
b1011 '
b1000 (
1+
0,
0/
02
15
#220
0#
0$
b1100 '
b1001 (
0+
1,
0.
11
#221
1#
b1101 '
b1010 (
1+
0,
1/
#222
0#
b1110 '
b1011 (
0+
1,
1.
#223
1#
1$
b1111 '
b1100 (
1+
0,
0/
12
#224
0#
0$
0%
b1110 &
b0000 '
b1110 (
0)
0*
0+
1-
0.
1/
01
04
#225
b0001 '
b1111 (
1+
1,
#226
1$
1%
b0010 '
b0000 (
1)
0+
0,
1.
0/
02
05
#227
b0011 '
b0001 (
1+
1,
#228
0$
b0100 '
b0010 (
0+
0,
0.
1/
11
#229
b0101 '
b0011 (
1+
1,
#230
1$
b0110 '
b0100 (
0+
0,
1.
0/
12
#231
b0111 '
b0101 (
1+
1,
#232
0$
0%
b1000 '
b0110 (
0+
0,
0.
1/
01
14
#233
b1001 '
b0111 (
1+
1,
#234
1$
1%
b1010 '
b1000 (
0+
0,
1.
0/
02
15
#235
b1011 '
b1001 (
1+
1,
#236
0$
b1100 '
b1010 (
0+
0,
0.
1/
11
#237
b1101 '
b1011 (
1+
1,
#238
1$
b1110 '
b1100 (
0+
0,
1.
0/
12
#239
b1111 '
b1101 (
1+
1,
#240
0$
0%
b1111 &
b0000 '
b1111 (
0)
1*
0+
0.
1/
01
04
#241
1#
1$
1%
b0001 '
b0000 (
1)
1+
0,
0/
02
05
#242
0#
b0010 '
b0001 (
0+
1,
1.
#243
1#
b0011 '
b0010 (
1+
0,
1/
#244
0#
0$
b0100 '
b0011 (
0+
1,
0.
11
#245
1#
1$
b0101 '
b0100 (
1+
0,
0/
12
#246
0#
b0110 '
b0101 (
0+
1,
1.
#247
1#
b0111 '
b0110 (
1+
0,
1/
#248
0#
0$
0%
b1000 '
b0111 (
0+
1,
0.
01
14
#249
1#
1$
1%
b1001 '
b1000 (
1+
0,
0/
02
15
#250
0#
b1010 '
b1001 (
0+
1,
1.
#251
1#
b1011 '
b1010 (
1+
0,
1/
#252
0#
0$
b1100 '
b1011 (
0+
1,
0.
11
#253
1#
1$
b1101 '
b1100 (
1+
0,
0/
12
#254
0#
b1110 '
b1101 (
0+
1,
1.
#255
1#
b1111 '
b1110 (
1+
0,
1/
